pocket/__init__.py
pocket/eqtl.py
pocket/genes_function_svm.py
pocket/pocket.py
pockt/__init__.py
pockt/eqtl.py
pockt/genes_function_svm.py
pockt/pockt.py
Gene_POCKET-0.0.4.dist-info/LICENSE
Gene_POCKET-0.0.4.dist-info/METADATA
Gene_POCKET-0.0.4.dist-info/WHEEL
Gene_POCKET-0.0.4.dist-info/top_level.txt
Gene_POCKET-0.0.4.dist-info/RECORD
