Metadata-Version: 2.1
Name: Gene-POCKET
Version: 0.0.4
Summary: a library for prioritizing the candidate genes by incorporating information of Knowledge-based gene sets, Effects of variants, GWAS and TWAS
Home-page: https://github.com/zhaouu/POCKET
Author: Hu Zhao
Author-email: zhaohu@webmail.hzau.edu.cn
License: MIT License
Keywords: candidate genes prioritization
Platform: any
Requires-Dist: numpy
Requires-Dist: scipy
Requires-Dist: scikit-learn
Requires-Dist: limix
Requires-Dist: pandas
Requires-Dist: joblib
